logmerge/__init__.py
logmerge/constants.py
logmerge/data_structures.py
logmerge/file_monitoring.py
logmerge/logging_config.py
logmerge/main.py
logmerge/main_window.py
logmerge/parsing_utils.py
logmerge/plugin_utils.py
logmerge/dialogs/__init__.py
logmerge/dialogs/add_files.py
logmerge/dialogs/column_configuration.py
logmerge/dialogs/file_discovery.py
logmerge/dialogs/simple_dialogs.py
logmerge/plugins/__init__.py
logmerge/plugins/canking_plugin.py
logmerge/plugins/dbglog_plugin.py
logmerge/plugins/syslog_plugin.py
logmerge/plugins/worldcan_plugin.py
logmerge/widgets/__init__.py
logmerge/widgets/file_list.py
logmerge/widgets/filter_panel.py
logmerge/widgets/log_table.py
logmerge/widgets/panels.py
logmerge-0.2.1.dist-info/licenses/LICENSE
logmerge-0.2.1.dist-info/METADATA
logmerge-0.2.1.dist-info/WHEEL
logmerge-0.2.1.dist-info/entry_points.txt
logmerge-0.2.1.dist-info/top_level.txt
logmerge-0.2.1.dist-info/RECORD
