Metadata-Version: 2.4
Name: logmerge
Version: 0.2.1
Summary: A GUI application for viewing and analyzing multiple log files with advanced filtering and merging capabilities
Author-email: Faisal Shah <faisal.shah@gmail.com>
Maintainer-email: Faisal Shah <faisal.shah@gmail.com>
Requires-Python: >=3.10
License-File: LICENSE
Requires-Dist: PyQt5
Provides-Extra: dev
Requires-Dist: pytest; extra == "dev"
Requires-Dist: black; extra == "dev"
Requires-Dist: ruff; extra == "dev"
Requires-Dist: mypy; extra == "dev"
Dynamic: license-file
